saupaket/__init__.py
saupaket/main.py
saupaket-0.1.0.dist-info/METADATA
saupaket-0.1.0.dist-info/WHEEL
saupaket-0.1.0.dist-info/RECORD
