Metadata-Version: 2.1
Name: saupaket
Version: 0.1.0
Summary: 
Author: Captain Solaris
Author-email: hello@spielprinzip.com
Requires-Python: >=3.12,<4.0
Classifier: Programming Language :: Python :: 3
Classifier: Programming Language :: Python :: 3.12
Classifier: Programming Language :: Python :: 3.13
Requires-Dist: quantum-quarks (>=0.1.1,<0.2.0)
Requires-Dist: requests (>=2.32.3,<3.0.0)
